wolfsoftware/ttfb/cli.py
wolfsoftware/ttfb/config.py
wolfsoftware/ttfb/exceptions.py
wolfsoftware/ttfb/globals.py
wolfsoftware/ttfb/main.py
wolfsoftware/ttfb/process.py
wolfsoftware/ttfb/results.py
wolfsoftware/ttfb/utils.py
wolfsoftware.ttfb-0.1.2.dist-info/LICENSE.md
wolfsoftware.ttfb-0.1.2.dist-info/METADATA
wolfsoftware.ttfb-0.1.2.dist-info/WHEEL
wolfsoftware.ttfb-0.1.2.dist-info/entry_points.txt
wolfsoftware.ttfb-0.1.2.dist-info/top_level.txt
wolfsoftware.ttfb-0.1.2.dist-info/RECORD
