Metadata-Version: 2.1
Name: wolfsoftware.ttfb
Version: 0.1.2
Summary: Display the time-to-first-byte for any given url.
Home-page: https://github.com/PlatformEngineersToolbox/time-to-first-byte-package
Author: Wolf Software
Author-email: pypi@wolfsoftware.com
License: MIT
Project-URL: Source, https://github.com/PlatformEngineersToolbox/time-to-first-byte-package
Project-URL: Tracker, https://github.com/PlatformEngineersToolbox/time-to-first-byte-package/issues/
Project-URL: Documentation, https://github.com/PlatformEngineersToolbox/time-to-first-byte-package
Project-URL: Sponsor, https://github.com/sponsors/WolfSoftware
Keywords: python,time-to-first-byte
Classifier: Development Status :: 4 - Beta
Classifier: Environment :: Console
Classifier: Intended Audience :: Developers
Classifier: License :: OSI Approved :: MIT License
Classifier: Programming Language :: Python :: 3
Classifier: Programming Language :: Python :: 3.9
Classifier: Programming Language :: Python :: 3.10
Classifier: Programming Language :: Python :: 3.11
Classifier: Programming Language :: Python :: 3.12
Classifier: Operating System :: OS Independent
Classifier: Topic :: Software Development
Requires-Python: >=3.9
License-File: LICENSE.md
Requires-Dist: colorama ==0.4.6
Requires-Dist: wolfsoftware.drawlines ==0.1.1
Requires-Dist: wolfsoftware.notify ==0.1.0
Requires-Dist: wolfsoftware.prereqs ==0.1.4
